Metadata-Version: 2.1
Name: pibooth-stillimage-camera
Version: 0.1.4
Summary: Dummy camera for pibooth, producing still images for testing
License: AGPLv3
Project-URL: Homepage, https://gitlab.com/wolface/wolfoto-project/pibooth-stillimage-camera
Keywords: Raspberry Pi,camera,photobooth,pibooth
Classifier: Development Status :: 5 - Production/Stable
Classifier: Environment :: Other Environment
Classifier: Intended Audience :: Developers
Classifier: Intended Audience :: End Users/Desktop
Classifier: License :: OSI Approved :: GNU Affero General Public License v3
Classifier: Operating System :: POSIX :: Linux
Classifier: Programming Language :: Python :: 3.7
Classifier: Programming Language :: Python :: 3.8
Classifier: Programming Language :: Python :: 3.9
Classifier: Natural Language :: English
Classifier: Topic :: Multimedia :: Graphics :: Capture :: Digital Camera
Requires-Python: >=3.6
License-File: LICENSE
